[
  {
    "region_code": "UKI",
    "region_level": 1,
    "homicide_count": 99,
    "homicide_rate": 1.1166026405960627,
    "violent_total_count": 246759,
    "violent_total_rate": 2783.148999907514,
    "assault_count": 64592,
    "assault_rate": 728.5211895088978,
    "robbery_count": 32730,
    "robbery_rate": 369.15560026978926,
    "sexual_assault_count": 27808,
    "sexual_assault_rate": 313.6412750474274,
    "population": 8866180,
    "period_start": "2025-01-01T00:00:00",
    "period_end": "2025-12-31T00:00:00",
    "source_url": "https://www.ons.gov.uk/file?uri=/peoplepopulationandcommunity/crimeandjustice/datasets/policeforceareadatatables/yearendingdecember2025/pfatablesyedec2025.xlsx",
    "region_name": "London"
  },
  {
    "region_code": "UKL",
    "region_level": 1,
    "homicide_count": 35,
    "homicide_rate": 1.1060303937152192,
    "violent_total_count": 106295,
    "violent_total_rate": 3359.0143057131213,
    "assault_count": 26106,
    "assault_rate": 824.9722702379862,
    "robbery_count": 1586,
    "robbery_rate": 50.11897726949537,
    "sexual_assault_count": 11437,
    "sexual_assault_rate": 361.4191317977418,
    "population": 3164470,
    "period_start": "2025-01-01T00:00:00",
    "period_end": "2025-12-31T00:00:00",
    "source_url": "https://www.ons.gov.uk/file?uri=/peoplepopulationandcommunity/crimeandjustice/datasets/policeforceareadatatables/yearendingdecember2025/pfatablesyedec2025.xlsx",
    "region_name": "Wales"
  },
  {
    "region_code": "UKG",
    "region_level": 1,
    "homicide_count": 66,
    "homicide_rate": 1.0943124932019983,
    "violent_total_count": 204733,
    "violent_total_rate": 3394.5739344049193,
    "assault_count": 53828,
    "assault_rate": 892.4947406678357,
    "robbery_count": 8915,
    "robbery_rate": 147.81508904387596,
    "sexual_assault_count": 21928,
    "sexual_assault_rate": 363.5770356202033,
    "population": 6031184,
    "period_start": "2025-01-01T00:00:00",
    "period_end": "2025-12-31T00:00:00",
    "source_url": "https://www.ons.gov.uk/file?uri=/peoplepopulationandcommunity/crimeandjustice/datasets/policeforceareadatatables/yearendingdecember2025/pfatablesyedec2025.xlsx",
    "region_name": "West Midlands (England)"
  },
  {
    "region_code": "UKF",
    "region_level": 1,
    "homicide_count": 45,
    "homicide_rate": 0.911865374627731,
    "violent_total_count": 149418,
    "violent_total_rate": 3027.757789913918,
    "assault_count": 44102,
    "assault_rate": 893.6685944851598,
    "robbery_count": 4651,
    "robbery_rate": 94.24635238652394,
    "sexual_assault_count": 17709,
    "sexual_assault_rate": 358.84942042849974,
    "population": 4934939,
    "period_start": "2025-01-01T00:00:00",
    "period_end": "2025-12-31T00:00:00",
    "source_url": "https://www.ons.gov.uk/file?uri=/peoplepopulationandcommunity/crimeandjustice/datasets/policeforceareadatatables/yearendingdecember2025/pfatablesyedec2025.xlsx",
    "region_name": "East Midlands (England)"
  },
  {
    "region_code": "UKC",
    "region_level": 1,
    "homicide_count": 21,
    "homicide_rate": 0.7900980398796342,
    "violent_total_count": 97957,
    "violent_total_rate": 3685.506366309016,
    "assault_count": 28411,
    "assault_rate": 1068.9274005247755,
    "robbery_count": 3493,
    "robbery_rate": 131.41964063331247,
    "sexual_assault_count": 11338,
    "sexual_assault_rate": 426.57769410263296,
    "population": 2657898,
    "period_start": "2025-01-01T00:00:00",
    "period_end": "2025-12-31T00:00:00",
    "source_url": "https://www.ons.gov.uk/file?uri=/peoplepopulationandcommunity/crimeandjustice/datasets/policeforceareadatatables/yearendingdecember2025/pfatablesyedec2025.xlsx",
    "region_name": "North East (England)"
  },
  {
    "region_code": "UKE",
    "region_level": 1,
    "homicide_count": 43,
    "homicide_rate": 0.7738726205666547,
    "violent_total_count": 224099,
    "violent_total_rate": 4033.118148752715,
    "assault_count": 55081,
    "assault_rate": 991.2948328705096,
    "robbery_count": 7153,
    "robbery_rate": 128.73281057937865,
    "sexual_assault_count": 22117,
    "sexual_assault_rate": 398.0404825365744,
    "population": 5556470,
    "period_start": "2025-01-01T00:00:00",
    "period_end": "2025-12-31T00:00:00",
    "source_url": "https://www.ons.gov.uk/file?uri=/peoplepopulationandcommunity/crimeandjustice/datasets/policeforceareadatatables/yearendingdecember2025/pfatablesyedec2025.xlsx",
    "region_name": "Yorkshire and The Humber"
  },
  {
    "region_code": "UKH",
    "region_level": 1,
    "homicide_count": 48,
    "homicide_rate": 0.7501761741859065,
    "violent_total_count": 179372,
    "violent_total_rate": 2803.3458482515503,
    "assault_count": 46310,
    "assault_rate": 723.7637213864443,
    "robbery_count": 4475,
    "robbery_rate": 69.93829957254025,
    "sexual_assault_count": 20422,
    "sexual_assault_rate": 319.16870477551214,
    "population": 6398497,
    "period_start": "2025-01-01T00:00:00",
    "period_end": "2025-12-31T00:00:00",
    "source_url": "https://www.ons.gov.uk/file?uri=/peoplepopulationandcommunity/crimeandjustice/datasets/policeforceareadatatables/yearendingdecember2025/pfatablesyedec2025.xlsx",
    "region_name": "East of England"
  },
  {
    "region_code": "UKK",
    "region_level": 1,
    "homicide_count": 37,
    "homicide_rate": 0.6418172378579887,
    "violent_total_count": 179642,
    "violent_total_rate": 3116.1441146833736,
    "assault_count": 43758,
    "assault_rate": 759.0442890321586,
    "robbery_count": 4701,
    "robbery_rate": 81.54548203163257,
    "sexual_assault_count": 21349,
    "sexual_assault_rate": 370.3285462440595,
    "population": 5764881,
    "period_start": "2025-01-01T00:00:00",
    "period_end": "2025-12-31T00:00:00",
    "source_url": "https://www.ons.gov.uk/file?uri=/peoplepopulationandcommunity/crimeandjustice/datasets/policeforceareadatatables/yearendingdecember2025/pfatablesyedec2025.xlsx",
    "region_name": "South West (England)"
  },
  {
    "region_code": "UKJ",
    "region_level": 1,
    "homicide_count": 59,
    "homicide_rate": 0.62906332258026,
    "violent_total_count": 266703,
    "violent_total_rate": 2843.611446137679,
    "assault_count": 70790,
    "assault_rate": 754.7693661941797,
    "robbery_count": 7237,
    "robbery_rate": 77.16154687310748,
    "sexual_assault_count": 29918,
    "sexual_assault_rate": 318.98841499925794,
    "population": 9379024,
    "period_start": "2025-01-01T00:00:00",
    "period_end": "2025-12-31T00:00:00",
    "source_url": "https://www.ons.gov.uk/file?uri=/peoplepopulationandcommunity/crimeandjustice/datasets/policeforceareadatatables/yearendingdecember2025/pfatablesyedec2025.xlsx",
    "region_name": "South East (England)"
  },
  {
    "region_code": "UKD",
    "region_level": 1,
    "homicide_count": 47,
    "homicide_rate": 0.6253232222559719,
    "violent_total_count": 286616,
    "violent_total_rate": 3813.3540568110134,
    "assault_count": 70382,
    "assault_rate": 936.414872953613,
    "robbery_count": 7916,
    "robbery_rate": 105.32039632719732,
    "sexual_assault_count": 28916,
    "sexual_assault_rate": 384.7201339309294,
    "population": 7516113,
    "period_start": "2025-01-01T00:00:00",
    "period_end": "2025-12-31T00:00:00",
    "source_url": "https://www.ons.gov.uk/file?uri=/peoplepopulationandcommunity/crimeandjustice/datasets/policeforceareadatatables/yearendingdecember2025/pfatablesyedec2025.xlsx",
    "region_name": "North West (England)"
  }
]